jenkins_terminal/__init__.py
jenkins_terminal/__main__.py
jenkins_terminal/build.py
jenkins_terminal/builds.py
jenkins_terminal/config.py
jenkins_terminal/output.py
jenkins_terminal/status.py
jenkins_terminal-0.7.1.dist-info/LICENSE
jenkins_terminal-0.7.1.dist-info/METADATA
jenkins_terminal-0.7.1.dist-info/WHEEL
jenkins_terminal-0.7.1.dist-info/entry_points.txt
jenkins_terminal-0.7.1.dist-info/RECORD
