Metadata-Version: 2.1
Name: jenkins-terminal
Version: 0.7.1
Summary: A CLI tool for Jenkins
License: MIT
Author: Loki
Author-email: yongxiang.zhan@outlook.com
Requires-Python: >=3.6.3,<4.0.0
Classifier: License :: OSI Approved :: MIT License
Classifier: Programming Language :: Python :: 3
Classifier: Programming Language :: Python :: 3.7
Classifier: Programming Language :: Python :: 3.8
Classifier: Programming Language :: Python :: 3.9
Classifier: Programming Language :: Python :: 3.10
Classifier: Programming Language :: Python :: 3.11
Classifier: Programming Language :: Python :: 3.12
Requires-Dist: python-jenkins (>=1.8.2,<2.0.0)
Requires-Dist: pyyaml (>=6.0.1,<7.0.0)
Requires-Dist: rich (>=12.6.0,<13.0.0)
Requires-Dist: typer (>=0.10.0,<0.11.0)
